hatch_regex_commit/__about__.py
hatch_regex_commit/__init__.py
hatch_regex_commit/exceptions.py
hatch_regex_commit/git.py
hatch_regex_commit/hooks.py
hatch_regex_commit/version_source.py
hatch_regex_commit-0.0.4.dist-info/METADATA
hatch_regex_commit-0.0.4.dist-info/WHEEL
hatch_regex_commit-0.0.4.dist-info/entry_points.txt
hatch_regex_commit-0.0.4.dist-info/licenses/LICENSE
hatch_regex_commit-0.0.4.dist-info/RECORD
