Metadata-Version: 2.4
Name: hatch-regex-commit
Version: 0.0.4
Summary: Hatch plugin to create a commit and tag when bumping version
Project-URL: Documentation, https://github.com/frankie567/hatch-regex-commit#readme
Project-URL: Issues, https://github.com/frankie567/hatch-regex-commit/issues
Project-URL: Source, https://github.com/frankie567/hatch-regex-commit
Author-email: François Voron <fvoron@gmail.com>
License-Expression: MIT
License-File: LICENSE
Classifier: Development Status :: 4 - Beta
Classifier: Framework :: Hatch
Classifier: Programming Language :: Python
Classifier: Programming Language :: Python :: 3.7
Classifier: Programming Language :: Python :: 3.8
Classifier: Programming Language :: Python :: 3.9
Classifier: Programming Language :: Python :: 3.10
Classifier: Programming Language :: Python :: 3.11
Classifier: Programming Language :: Python :: Implementation :: CPython
Classifier: Programming Language :: Python :: Implementation :: PyPy
Requires-Python: >=3.7
Requires-Dist: hatchling
